postgres_copy_binary_extension_module-0.6.0.dist-info/METADATA
postgres_copy_binary_extension_module-0.6.0.dist-info/WHEEL
postgres_copy_binary_extension_module/__init__.py
postgres_copy_binary_extension_module/postgres_copy_binary_extension_module.cpython-37m-s390x-linux-gnu.so
postgres_copy_binary_extension_module-0.6.0.dist-info/RECORD
