Metadata-Version: 2.1
Name: postgres-copy-binary-extension-module
Version: 0.6.0
Classifier: Programming Language :: Rust
Classifier: Programming Language :: Python :: Implementation :: CPython
Classifier: Programming Language :: Python :: Implementation :: PyPy
Requires-Dist: pyarrow~=11.0.0
Requires-Python: >=3.7
